ladata/__init__.py
ladata/ladata.py
ladata-0.1.0.dist-info/AUTHORS.rst
ladata-0.1.0.dist-info/LICENSE
ladata-0.1.0.dist-info/METADATA
ladata-0.1.0.dist-info/WHEEL
ladata-0.1.0.dist-info/top_level.txt
ladata-0.1.0.dist-info/RECORD
