Metadata-Version: 2.1
Name: ladata
Version: 0.1.0
Summary: This packages contains the tools necessary to build an LAD model.
Home-page: https://github.com/robypoteau/ladata
Author: Roby Poteau
Author-email: robypoteau@gmail.com
License: BSD license
Keywords: ladata
Platform: UNKNOWN
Classifier: Development Status :: 2 - Pre-Alpha
Classifier: Intended Audience :: Developers
Classifier: License :: OSI Approved :: BSD License
Classifier: Natural Language :: English
Classifier: Programming Language :: Python :: 3
Classifier: Programming Language :: Python :: 3.6
Classifier: Programming Language :: Python :: 3.7
Classifier: Programming Language :: Python :: 3.8
Requires-Python: >=3.6
